honganh_tets/__init__.py
honganh_tets/cli.py
honganh_tets/honganh_tets.py
honganh_tets-0.0.1.dist-info/DESCRIPTION.rst
honganh_tets-0.0.1.dist-info/METADATA
honganh_tets-0.0.1.dist-info/RECORD
honganh_tets-0.0.1.dist-info/WHEEL
honganh_tets-0.0.1.dist-info/metadata.json
honganh_tets-0.0.1.dist-info/top_level.txt
