Metadata-Version: 2.0
Name: honganh-tets
Version: 0.0.1
Summary: aaaa
Home-page: https://github.com/honganhbk/honganh_tets
Author: Hong anh
Author-email: honganh.95.bk@gmail.com
License: MIT license
Keywords: honganh_tets
Platform: UNKNOWN
Classifier: Development Status :: 2 - Pre-Alpha
Classifier: Intended Audience :: Developers
Classifier: License :: OSI Approved :: MIT License
Classifier: Natural Language :: English
Classifier: Programming Language :: Python :: 2
Classifier: Programming Language :: Python :: 2.7
Classifier: Programming Language :: Python :: 3
Classifier: Programming Language :: Python :: 3.4
Classifier: Programming Language :: Python :: 3.5
Classifier: Programming Language :: Python :: 3.6
Classifier: Programming Language :: Python :: 3.7
Requires-Dist: Click (>=6.0)
